glareclient/__init__.py
glareclient/_i18n.py
glareclient/client.py
glareclient/exc.py
glareclient/shell.py
glareclient/common/__init__.py
glareclient/common/exceptions.py
glareclient/common/http.py
glareclient/common/keycloak_auth.py
glareclient/common/progressbar.py
glareclient/common/utils.py
glareclient/osc/__init__.py
glareclient/osc/plugin.py
glareclient/osc/v1/__init__.py
glareclient/osc/v1/artifacts.py
glareclient/osc/v1/blobs.py
glareclient/tests/__init__.py
glareclient/tests/unit/__init__.py
glareclient/tests/unit/base.py
glareclient/tests/unit/fakes.py
glareclient/tests/unit/test_common_http.py
glareclient/tests/unit/test_progressbar.py
glareclient/tests/unit/test_shell.py
glareclient/tests/unit/test_utils.py
glareclient/tests/unit/osc/__init__.py
glareclient/tests/unit/osc/test_plugin.py
glareclient/tests/unit/osc/v1/__init__.py
glareclient/tests/unit/osc/v1/fakes.py
glareclient/tests/unit/osc/v1/fakes_schemas.py
glareclient/tests/unit/osc/v1/test_artifacts.py
glareclient/tests/unit/osc/v1/test_blob.py
glareclient/tests/unit/v1/__init__.py
glareclient/tests/unit/v1/test_artifacts.py
glareclient/tests/unit/var/badcert.crt
glareclient/tests/unit/var/ca.crt
glareclient/tests/unit/var/certificate.crt
glareclient/tests/unit/var/expired-cert.crt
glareclient/tests/unit/var/privatekey.key
glareclient/tests/unit/var/wildcard-certificate.crt
glareclient/tests/unit/var/wildcard-san-certificate.crt
glareclient/v1/__init__.py
glareclient/v1/artifacts.py
glareclient/v1/client.py
glareclient/v1/versions.py
python_glareclient-0.5.3.dist-info/METADATA
python_glareclient-0.5.3.dist-info/RECORD
python_glareclient-0.5.3.dist-info/WHEEL
python_glareclient-0.5.3.dist-info/entry_points.txt
python_glareclient-0.5.3.dist-info/pbr.json
python_glareclient-0.5.3.dist-info/top_level.txt
