Metadata-Version: 2.1
Name: python-glareclient
Version: 0.5.3
Summary: Glare Artifact Repository
Home-page: http://docs.openstack.org/developer/python-glareclient
Author: OpenStack
Author-email: openstack-dev@lists.openstack.org
License: Apache License, Version 2.0
Platform: UNKNOWN
Classifier: Development Status :: 5 - Production/Stable
Classifier: Environment :: Console
Classifier: Environment :: OpenStack
Classifier: Intended Audience :: Information Technology
Classifier: Intended Audience :: System Administrators
Classifier: License :: OSI Approved :: Apache Software License
Classifier: Operating System :: POSIX :: Linux
Classifier: Programming Language :: Python
Classifier: Programming Language :: Python :: 2
Classifier: Programming Language :: Python :: 2.7
Classifier: Programming Language :: Python :: 3
Classifier: Programming Language :: Python :: 3.4
Classifier: Programming Language :: Python :: 3.5
Requires-Dist: pbr (!=2.1.0,>=2.0.0)
Requires-Dist: Babel (!=2.4.0,>=2.3.4)
Requires-Dist: PrettyTable (<0.8,>=0.7.1)
Requires-Dist: keystoneauth1 (>=3.2.0)
Requires-Dist: requests (>=2.14.2)
Requires-Dist: six (>=1.9.0)
Requires-Dist: oslo.utils (>=3.31.0)
Requires-Dist: oslo.i18n (>=3.15.3)
Requires-Dist: oslo.log (>=3.30.0)
Requires-Dist: osc-lib (>=1.7.0)
